voxio/__init__.py
voxio/caching.py
voxio/clean/__init__.py
voxio/clean/single_big_obj_artifact_purge.py
voxio/cli.py
voxio/crop.py
voxio/read.py
voxio/utils/__init__.py
voxio/utils/distance.py
voxio/utils/interpolate.py
voxio/utils/io.py
voxio/utils/misc.py
voxio/utils/typings.py
voxio/volume_info/__init__.py
voxio/volume_info/read.py
voxio/volume_info/volume_info.py
voxio/workflows/__init__.py
voxio/workflows/label_binary_image.py
voxio-1.0.1.dist-info/LICENSE.md
voxio-1.0.1.dist-info/METADATA
voxio-1.0.1.dist-info/WHEEL
voxio-1.0.1.dist-info/entry_points.txt
voxio-1.0.1.dist-info/RECORD
